README.rst
setup.py
django_views_breadcrumbs.egg-info/PKG-INFO
django_views_breadcrumbs.egg-info/SOURCES.txt
django_views_breadcrumbs.egg-info/dependency_links.txt
django_views_breadcrumbs.egg-info/requires.txt
django_views_breadcrumbs.egg-info/top_level.txt
views_breadcrumbs/__init__.py
views_breadcrumbs/conf.py
views_breadcrumbs/middleware.py
views_breadcrumbs/models.py
views_breadcrumbs/views.py
views_breadcrumbs/templatetags/__init__.py
views_breadcrumbs/templatetags/breadcrumbs.py