Metadata-Version: 1.1
Name: django-views-breadcrumbs
Version: 0.1.dev3
Summary: Breadcrumbs support on django class based views
Home-page: https://github.com/nimoism/django-views-breadcrumbs
Author: Dmitry Puhov
Author-email: dmitry.puhov@gmail.com
License: UNKNOWN
Platform: any
Classifier: Development Status :: 4 - Beta
Classifier: Intended Audience :: Developers
Classifier: Environment :: Web Environment
Classifier: Programming Language :: Python :: 2
Classifier: Programming Language :: Python :: 2.6
Classifier: Programming Language :: Python :: 2.7
Classifier: Framework :: Django
